{
  "version": "v193",
  "updated": "2026-07-19T13:43:58.601Z",
  "summary": {
    "settledFixtures": 172,
    "settledDecisions": 347,
    "reviewedLosses": 56,
    "teamProfiles": 76,
    "leagueProfiles": 16,
    "matchupProfiles": 39,
    "activePatternBreakers": 0,
    "upsetResistantTeams": 0
  },
  "patternBreakers": [],
  "upsetResistant": [],
  "dangerousUnderdogs": [],
  "volatileLeagues": [],
  "stableLeagues": [],
  "commonMissCauses": [],
  "recentLossReviews": [],
  "methodology": {"forwardOnly":true,"decayHalfLifeDays":120,"positiveAdjustmentCap":2,"oneMarketOnly":true}
}
