{
  "generatedAt": "2026-07-23T03:46:03.668Z",
  "expectedFromManifest": 2456,
  "discoveredExactFixtures": 2456,
  "savedActiveFixtures": 2456,
  "enrichedFixtures": 2456,
  "fixtureOnlyFallbacks": 0,
  "finalCoveragePercent": 100,
  "dates": {
    "2026-07-21": {
      "discovered": 188,
      "saved": 188,
      "enriched": 188,
      "fixtureOnly": 0
    },
    "2026-07-22": {
      "discovered": 208,
      "saved": 208,
      "enriched": 208,
      "fixtureOnly": 0
    },
    "2026-07-23": {
      "discovered": 134,
      "saved": 134,
      "enriched": 134,
      "fixtureOnly": 0
    },
    "2026-07-24": {
      "discovered": 261,
      "saved": 261,
      "enriched": 261,
      "fixtureOnly": 0
    },
    "2026-07-25": {
      "discovered": 864,
      "saved": 864,
      "enriched": 864,
      "fixtureOnly": 0
    },
    "2026-07-26": {
      "discovered": 452,
      "saved": 452,
      "enriched": 452,
      "fixtureOnly": 0
    },
    "2026-07-27": {
      "discovered": 86,
      "saved": 86,
      "enriched": 86,
      "fixtureOnly": 0
    },
    "2026-07-28": {
      "discovered": 127,
      "saved": 127,
      "enriched": 127,
      "fixtureOnly": 0
    },
    "2026-07-29": {
      "discovered": 136,
      "saved": 136,
      "enriched": 136,
      "fixtureOnly": 0
    }
  }
}
