{
  "generatedAt": "2026-07-20T22:42:32.303Z",
  "windowStart": "2026-07-20",
  "windowEnd": "2026-07-26",
  "totalSavedMatches": 6201,
  "totalGamesInWindow": 2089,
  "daysWithGames": 7,
  "daysWithoutGames": [],
  "discoveryFixtureCount": 3140,
  "coveragePercent": 100,
  "dates": [
    {
      "date": "2026-07-20",
      "games": 66,
      "leagues": 28,
      "enriched": 66,
      "fixtureOnly": 0,
      "upcoming": 25,
      "live": 1,
      "finished": 39
    },
    {
      "date": "2026-07-21",
      "games": 180,
      "leagues": 31,
      "enriched": 180,
      "fixtureOnly": 0,
      "upcoming": 180,
      "live": 0,
      "finished": 0
    },
    {
      "date": "2026-07-22",
      "games": 201,
      "leagues": 38,
      "enriched": 201,
      "fixtureOnly": 0,
      "upcoming": 201,
      "live": 0,
      "finished": 0
    },
    {
      "date": "2026-07-23",
      "games": 128,
      "leagues": 27,
      "enriched": 128,
      "fixtureOnly": 0,
      "upcoming": 128,
      "live": 0,
      "finished": 0
    },
    {
      "date": "2026-07-24",
      "games": 241,
      "leagues": 68,
      "enriched": 241,
      "fixtureOnly": 0,
      "upcoming": 241,
      "live": 0,
      "finished": 0
    },
    {
      "date": "2026-07-25",
      "games": 836,
      "leagues": 138,
      "enriched": 836,
      "fixtureOnly": 0,
      "upcoming": 836,
      "live": 0,
      "finished": 0
    },
    {
      "date": "2026-07-26",
      "games": 437,
      "leagues": 108,
      "enriched": 437,
      "fixtureOnly": 0,
      "upcoming": 437,
      "live": 0,
      "finished": 0
    }
  ]
}
