{
  "generatedAt": "2026-07-18T04:53:19.989Z",
  "windowStart": "2026-07-18",
  "windowEnd": "2026-07-24",
  "totalSavedMatches": 4738,
  "totalGamesInWindow": 1675,
  "daysWithGames": 7,
  "daysWithoutGames": [],
  "discoveryFixtureCount": 2056,
  "coveragePercent": 100,
  "dates": [
    {
      "date": "2026-07-18",
      "games": 718,
      "leagues": 105,
      "enriched": 718,
      "fixtureOnly": 0,
      "upcoming": 701,
      "live": 4,
      "finished": 13
    },
    {
      "date": "2026-07-19",
      "games": 189,
      "leagues": 62,
      "enriched": 189,
      "fixtureOnly": 0,
      "upcoming": 189,
      "live": 0,
      "finished": 0
    },
    {
      "date": "2026-07-20",
      "games": 53,
      "leagues": 26,
      "enriched": 53,
      "fixtureOnly": 0,
      "upcoming": 53,
      "live": 0,
      "finished": 0
    },
    {
      "date": "2026-07-21",
      "games": 173,
      "leagues": 31,
      "enriched": 173,
      "fixtureOnly": 0,
      "upcoming": 173,
      "live": 0,
      "finished": 0
    },
    {
      "date": "2026-07-22",
      "games": 188,
      "leagues": 37,
      "enriched": 188,
      "fixtureOnly": 0,
      "upcoming": 188,
      "live": 0,
      "finished": 0
    },
    {
      "date": "2026-07-23",
      "games": 125,
      "leagues": 26,
      "enriched": 125,
      "fixtureOnly": 0,
      "upcoming": 125,
      "live": 0,
      "finished": 0
    },
    {
      "date": "2026-07-24",
      "games": 229,
      "leagues": 67,
      "enriched": 229,
      "fixtureOnly": 0,
      "upcoming": 229,
      "live": 0,
      "finished": 0
    }
  ]
}
